{
	"test_object":{
		"test_sub_object":{
			"description": "test_description",
			"array": ["string_index", 1234, true, null]
		}
	},

	"1999":{
		"monthly_data":{
			"description": "gun_bg_checks, ...",
			"jan": [591355],
			"feb": [696323],
			"mar": [753083],
			"apr": [646712],
			"may": [576272],
			"jun": [569493],
			"jul": [589476],
			"aug": [703394],
			"sep": [808627],
			"oct": [945701],
			"nov": [1004333],
			"dec": [1253354]
			}
	},

	"2000":{
		"monthly_data":{
			"description": "gun_bg_checks, ...",
			"jan": [639972],
			"feb": [707070],
			"mar": [736543],
			"apr": [617689],
			"may": [538648],
			"jun": [550561],
			"jul": [542520],
			"aug": [682501],
			"sep": [782087],
			"oct": [845886],
			"nov": [898598],
			"dec": [1000962]
		}
	},

	"2001":{
		"monthly_data":{
			"description": "gun_bg_checks, ...",
			"jan": [640528],
			"feb": [675156],
			"mar": [729532],
			"apr": [594723],
			"may": [543501],
			"jun": [540491],
			"jul": [539498],
			"aug": [707288],
			"sep": [864038],
			"oct": [1029691],
			"nov": [983186],
			"dec": [1062559]
		}
	},

	"2002":{
		"monthly_data":{
			"description": "gun_bg_checks, ...",
			"jan": [665803],
			"feb": [694668],
			"mar": [714665],
			"apr": [627745],
			"may": [569247],
			"jun": [518351],
			"jul": [535594],
			"aug": [693139],
			"sep": [724123],
			"oct": [849281],
			"nov": [887647],
			"dec": [974059]
		}
	},

	"2003":{
		"monthly_data":{
			"description": "gun_bg_checks, ...",
			"jan": [653751],
			"feb": [708281],
			"mar": [736864],
			"apr": [622831],
			"may": [567436],
			"jun": [529334],
			"jul": [533289],
			"aug": [683517],
			"sep": [738371],
			"oct": [856863],
			"nov": [842932],
			"dec": [1008118]
		}
	},

	"2004":{
		"monthly_data":{
			"description": "gun_bg_checks, ...",
			"jan": [665000],
			"feb": [723654],
			"mar": [738298],
			"apr": [642589],
			"may": [542456],
			"jun": [546847],
			"jul": [561773],
			"aug": [666598],
			"sep": [740260],
			"oct": [865741],
			"nov": [890754],
			"dec": [1073701]
		}
	},

	"2005":{
		"monthly_data":{
			"description": "gun_bg_checks, ...",
			"jan": [685811],
			"feb": [743070],
			"mar": [768290],
			"apr": [658954],
			"may": [557058],
			"jun": [555560],
			"jul": [561358],
			"aug": [687012],
			"sep": [791353],
			"oct": [852478],
			"nov": [927419],
			"dec": [1164582]
		}
	},

	"2006":{
		"monthly_data":{
			"description": "gun_bg_checks, ...",
			"jan": [775518],
			"feb": [820679],
			"mar": [845219],
			"apr": [700373],
			"may": [626270],
			"jun": [616097],
			"jul": [631156],
			"aug": [838070],
			"sep": [919487],
			"oct": [970030],
			"nov": [1045194],
			"dec": [1253840]
		}
	},

	"2007":{
		"monthly_data":{
			"description": "gun_bg_checks, ...",
			"jan": [894608],
			"feb": [914954],
			"mar": [975806],
			"apr": [840271],
			"may": [803051],
			"jun": [792943],
			"jul": [757884],
			"aug": [917358],
			"sep": [944889],
			"oct": [1025123],
			"nov": [1079923],
			"dec": [1230525]
		}
	},

	"2008":{
		"monthly_data":{
			"description": "gun_bg_checks, ...",
			"jan": [942556],
			"feb": [1021130],
			"mar": [1040863],
			"apr": [940961],
			"may": [886183],
			"jun": [819891],
			"jul": [891224],
			"aug": [956872],
			"sep": [973003],
			"oct": [1183279],
			"nov": [1529635],
			"dec": [1523426]
		}
	},

	"2009":{
		"monthly_data":{
			"description": "gun_bg_checks, ...",
			"jan": [1213885],
			"feb": [1259078],
			"mar": [1345096],
			"apr": [1225980],
			"may": [1023102],
			"jun": [968145],
			"jul": [966162],
			"aug": [1074757],
			"sep": [1093230],
			"oct": [1233982],
			"nov": [1223252],
			"dec": [1407155]
		}
	},

	"2010":{
		"monthly_data":{
			"description": "gun_bg_checks, ...",
			"jan": [1119229],
			"feb": [1243211],
			"mar": [1300100],
			"apr": [1233761],
			"may": [1016876],
			"jun": [1005876],
			"jul": [1069792],
			"aug": [1089374],
			"sep": [1145798],
			"oct": [1368184],
			"nov": [1296223],
			"dec": [1521192]
		}
	},

	"2011":{
		"monthly_data":{
			"description": "gun_bg_checks, ...",
			"jan": [1323336],
			"feb": [1473513],
			"mar": [1449724],
			"apr": [1351255],
			"may": [1230953],
			"jun": [1168322],
			"jul": [1157041],
			"aug": [1310041],
			"sep": [1253752],
			"oct": [1340273],
			"nov": [1534414],
			"dec": [1862327]
		}
	},

	"2012":{
		"monthly_data":{
			"description": "gun_bg_checks, ...",
			"jan": [1377301],
			"feb": [1749903],
			"mar": [1727881],
			"apr": [1427343],
			"may": [1316226],
			"jun": [1302660],
			"jul": [1300704],
			"aug": [1526206],
			"sep": [1459363],
			"oct": [1614032],
			"nov": [2006919],
			"dec": [2783765]
		}
	},

	"2013":{
		"monthly_data":{
			"description": "gun_bg_checks, ...",
			"jan": [2495440],
			"feb": [2309393],
			"mar": [2209407],
			"apr": [1714433],
			"may": [1435917],
			"jun": [1281351],
			"jul": [1283912],
			"aug": [1419088],
			"sep": [1401562],
			"oct": [1687599],
			"nov": [1813643],
			"dec": [2041528]
		}
	},

	"2014":{
		"monthly_data":{
			"description": "gun_bg_checks, ...",
			"jan": [1660355],
			"feb": [2086863],
			"mar": [2488842],
			"apr": [1742946],
			"may": [1485259],
			"jun": [1382975],
			"jul": [1402228],
			"aug": [1546497],
			"sep": [1456032],
			"oct": [1603469],
			"nov": [1803397],
			"dec": [2309684]
		}
	},

	"2015":{
		"monthly_data":{
			"description": "gun_bg_checks, ...",
			"jan": [1772794],
			"feb": [1859584],
			"mar": [2012488],
			"apr": [1711340],
			"may": [1580980],
			"jun": [1529057],
			"jul": [1600832],
			"aug": [1745410],
			"sep": [1795102],
			"oct": [1976759],
			"nov": [2243030],
			"dec": [3314594]
		}
	},

	"2016":{
		"monthly_data":{
			"description": "gun_bg_checks, ...",
			"jan": [2545802],
			"feb": [2613074],
			"mar": [2523265],
			"apr": [2145865],
			"may": [1870000],
			"jun": [2131485],
			"jul": [2197169],
			"aug": [1853815],
			"sep": [1992219],
			"oct": [2333539],
			"nov": [2561281],
			"dec": [2771159]
		}
	},

	"2017":{
		"monthly_data":{
			"description": "gun_bg_checks, ...",
			"jan": [2043184],
			"feb": [2234817],
			"mar": [2433092],
			"apr": [2045564],
			"may": [1942677],
			"jun": [1901768],
			"jul": [1742546],
			"aug": [1925146],
			"sep": [1967104],
			"oct": [2030391],
			"nov": [2382788],
			"dec": [2586138]
		}
	},

	"2018":{
		"monthly_data":{
			"description": "gun_bg_checks, ...",
			"jan": [2030530],
			"feb": [2333193],
			"mar": [2767699],
			"apr": [2223213],
			"may": [2002992],
			"jun": [1935691],
			"jul": [1835318],
			"aug": [2073296],
			"sep": [1956681],
			"oct": [2086895],
			"nov": [2393043],
			"dec": [2543385]
		}
	},

	"2019":{
		"monthly_data":{
			"description": "gun_bg_checks, ...",
			"jan": [2165094],
			"feb": [2053886],
			"mar": [2644851],
			"apr": [2334249],
			"may": [2349309],
			"jun": [2312309],
			"jul": [2030661],
			"aug": [2366824],
			"sep": [2207312],
			"oct": [2393609],
			"nov": [2574752],
			"dec": [2936894]
		}
	},

	"2020":{
		"monthly_data":{
			"description": "gun_bg_checks, ...",
			"jan": [2702702],
			"feb": [2802467],
			"mar": [3740688],
			"apr": [2911128],
			"may": [3091455],
			"jun": [3931607],
			"jul": [3639224],
			"aug": null,
			"sep": null,
			"oct": null,
			"nov": null,
			"dec": null
		}
	}

}